<annotation verified="yes">
    <folder>Annotation</folder>
    <filename>7836.jpg</filename>
    <path>pollengermination2-PascalVOC-export/Annotations/7836.jpg</path>
    <source>
        <database>Unknown</database>
    </source>
    <size>
        <width>320</width>
        <height>169</height>
        <depth>3</depth>
    </size>
    <segmented>0</segmented>
    <object>
    <name>germinated</name>
    <pose>Unspecified</pose>
    <truncated>0</truncated>
    <difficult>0</difficult>
    <bndbox>
        <xmin>50.45752431832108</xmin>
        <ymin>30.11905452436195</ymin>
        <xmax>57.777781767003674</xmax>
        <ymax>40.05254652549938</ymax>
    </bndbox>
</object><object>
    <name>germinated</name>
    <pose>Unspecified</pose>
    <truncated>0</truncated>
    <difficult>0</difficult>
    <bndbox>
        <xmin>80.7843137254902</xmin>
        <ymin>70.89863689095128</ymin>
        <xmax>89.67321059283088</xmax>
        <ymax>77.43382238401338</ymax>
    </bndbox>
</object><object>
    <name>germinated</name>
    <pose>Unspecified</pose>
    <truncated>0</truncated>
    <difficult>0</difficult>
    <bndbox>
        <xmin>94.11764705882352</xmin>
        <ymin>5.808149651972157</ymin>
        <xmax>103.00654392616421</xmax>
        <ymax>15.48022609631036</ymax>
    </bndbox>
</object><object>
    <name>germinated</name>
    <pose>Unspecified</pose>
    <truncated>0</truncated>
    <difficult>0</difficult>
    <bndbox>
        <xmin>305.3594851026348</xmin>
        <ymin>92.85687354988399</ymin>
        <xmax>311.37254901960785</xmax>
        <ymax>103.31317273204121</ymax>
    </bndbox>
</object><object>
    <name>germinated</name>
    <pose>Unspecified</pose>
    <truncated>0</truncated>
    <difficult>0</difficult>
    <bndbox>
        <xmin>219.08497529871323</xmin>
        <ymin>10.774889669396208</ymin>
        <xmax>225.62093098958334</xmax>
        <ymax>20.18556252322451</ymax>
    </bndbox>
</object><object>
    <name>germinated</name>
    <pose>Unspecified</pose>
    <truncated>0</truncated>
    <difficult>0</difficult>
    <bndbox>
        <xmin>116.60132314644608</xmin>
        <ymin>27.243567163595745</ymin>
        <xmax>125.7516419653799</xmax>
        <ymax>34.30157180396697</ymax>
    </bndbox>
</object><object>
    <name>nongerminated</name>
    <pose>Unspecified</pose>
    <truncated>0</truncated>
    <difficult>0</difficult>
    <bndbox>
        <xmin>178.56210746017157</xmin>
        <ymin>100.43769733756434</ymin>
        <xmax>185.09803921568627</xmax>
        <ymax>106.97288283062645</ymax>
    </bndbox>
</object><object>
    <name>nongerminated</name>
    <pose>Unspecified</pose>
    <truncated>0</truncated>
    <difficult>0</difficult>
    <bndbox>
        <xmin>280.78431372549016</xmin>
        <ymin>17.310081145602975</ymin>
        <xmax>287.5817153033088</xmax>
        <ymax>23.845272621809745</ymax>
    </bndbox>
</object><object>
    <name>nongerminated</name>
    <pose>Unspecified</pose>
    <truncated>0</truncated>
    <difficult>0</difficult>
    <bndbox>
        <xmin>293.59477922028185</xmin>
        <ymin>53.122917511623584</ymin>
        <xmax>299.08497529871323</xmax>
        <ymax>59.919518561484914</ymax>
    </bndbox>
</object><object>
    <name>nongerminated</name>
    <pose>Unspecified</pose>
    <truncated>0</truncated>
    <difficult>0</difficult>
    <bndbox>
        <xmin>295.16340667126224</xmin>
        <ymin>19.92415893271462</ymin>
        <xmax>301.1764705882353</xmax>
        <ymax>26.45934442577672</ymax>
    </bndbox>
</object><object>
    <name>nongerminated</name>
    <pose>Unspecified</pose>
    <truncated>0</truncated>
    <difficult>0</difficult>
    <bndbox>
        <xmin>286.5359556908701</xmin>
        <ymin>62.79500592225112</ymin>
        <xmax>291.7647058823529</xmax>
        <ymax>69.06878782480332</ymax>
    </bndbox>
</object><object>
    <name>nongerminated</name>
    <pose>Unspecified</pose>
    <truncated>0</truncated>
    <difficult>0</difficult>
    <bndbox>
        <xmin>137.2549019607843</xmin>
        <ymin>94.16391543501214</ymin>
        <xmax>142.7450980392157</xmax>
        <ymax>100.17628178076512</ymax>
    </bndbox>
</object><object>
    <name>nongerminated</name>
    <pose>Unspecified</pose>
    <truncated>0</truncated>
    <difficult>0</difficult>
    <bndbox>
        <xmin>151.63399490655638</xmin>
        <ymin>132.5908295881444</ymin>
        <xmax>156.60132314644608</xmax>
        <ymax>138.60319593389738</ymax>
    </bndbox>
</object><object>
    <name>nongerminated</name>
    <pose>Unspecified</pose>
    <truncated>0</truncated>
    <difficult>0</difficult>
    <bndbox>
        <xmin>238.16995059742646</xmin>
        <ymin>116.12215209394486</ymin>
        <xmax>244.1830145143995</xmax>
        <ymax>123.18015673431609</ymax>
    </bndbox>
</object><object>
    <name>nongerminated</name>
    <pose>Unspecified</pose>
    <truncated>0</truncated>
    <difficult>0</difficult>
    <bndbox>
        <xmin>220.91504863664215</xmin>
        <ymin>148.2752843445249</ymin>
        <xmax>227.18955844056373</xmax>
        <ymax>155.59470454169536</ymax>
    </bndbox>
</object><object>
    <name>nongerminated</name>
    <pose>Unspecified</pose>
    <truncated>0</truncated>
    <difficult>0</difficult>
    <bndbox>
        <xmin>188.49674000459558</xmin>
        <ymin>20.44697209687908</ymin>
        <xmax>195.0326956954657</xmax>
        <ymax>26.72075998257595</ymax>
    </bndbox>
</object><object>
    <name>nongerminated</name>
    <pose>Unspecified</pose>
    <truncated>0</truncated>
    <difficult>0</difficult>
    <bndbox>
        <xmin>31.11111510033701</xmin>
        <ymin>95.7323609106502</ymin>
        <xmax>37.38562490425858</xmax>
        <ymax>102.79036555102142</ymax>
    </bndbox>
</object><object>
    <name>nongerminated</name>
    <pose>Unspecified</pose>
    <truncated>0</truncated>
    <difficult>0</difficult>
    <bndbox>
        <xmin>48.366017061121326</xmin>
        <ymin>2.4098491270414915</ymin>
        <xmax>54.640526865042894</xmax>
        <ymax>8.683631029593695</ymax>
    </bndbox>
</object>
</annotation>
