<annotation verified="yes">
    <folder>Annotation</folder>
    <filename>9808.jpg</filename>
    <path>pollengermination2-PascalVOC-export/Annotations/9808.jpg</path>
    <source>
        <database>Unknown</database>
    </source>
    <size>
        <width>320</width>
        <height>169</height>
        <depth>3</depth>
    </size>
    <segmented>0</segmented>
    <object>
    <name>germinated</name>
    <pose>Unspecified</pose>
    <truncated>0</truncated>
    <difficult>0</difficult>
    <bndbox>
        <xmin>190.58823529411765</xmin>
        <ymin>9.467853767412722</ymin>
        <xmax>199.73857804840688</xmax>
        <ymax>16.264448834129386</ymax>
    </bndbox>
</object><object>
    <name>germinated</name>
    <pose>Unspecified</pose>
    <truncated>0</truncated>
    <difficult>0</difficult>
    <bndbox>
        <xmin>294.11764705882354</xmin>
        <ymin>25.413718097447795</ymin>
        <xmax>301.6993623621324</xmax>
        <ymax>36.65424001742405</ymax>
    </bndbox>
</object><object>
    <name>nongerminated</name>
    <pose>Unspecified</pose>
    <truncated>0</truncated>
    <difficult>0</difficult>
    <bndbox>
        <xmin>250.19607843137254</xmin>
        <ymin>43.97366021459451</ymin>
        <xmax>256.7320341222426</xmax>
        <ymax>50.50884570765661</ymax>
    </bndbox>
</object><object>
    <name>nongerminated</name>
    <pose>Unspecified</pose>
    <truncated>0</truncated>
    <difficult>0</difficult>
    <bndbox>
        <xmin>309.01960784313724</xmin>
        <ymin>27.76638631090487</ymin>
        <xmax>316.86274509803917</xmax>
        <ymax>35.34721009858523</ymax>
    </bndbox>
</object><object>
    <name>nongerminated</name>
    <pose>Unspecified</pose>
    <truncated>0</truncated>
    <difficult>0</difficult>
    <bndbox>
        <xmin>186.40524471507354</xmin>
        <ymin>29.857650933852053</ymin>
        <xmax>191.89544079350492</xmax>
        <ymax>35.87001727960502</ymax>
    </bndbox>
</object><object>
    <name>nongerminated</name>
    <pose>Unspecified</pose>
    <truncated>0</truncated>
    <difficult>0</difficult>
    <bndbox>
        <xmin>187.18955844056373</xmin>
        <ymin>2.932662291205953</ymin>
        <xmax>192.94117647058823</xmax>
        <ymax>7.115185553955644</ymax>
    </bndbox>
</object><object>
    <name>nongerminated</name>
    <pose>Unspecified</pose>
    <truncated>0</truncated>
    <difficult>0</difficult>
    <bndbox>
        <xmin>181.69936236213235</xmin>
        <ymin>4.239704176334107</ymin>
        <xmax>189.01960784313724</xmax>
        <ymax>9.467853767412722</ymax>
    </bndbox>
</object><object>
    <name>nongerminated</name>
    <pose>Unspecified</pose>
    <truncated>0</truncated>
    <difficult>0</difficult>
    <bndbox>
        <xmin>175.16340667126227</xmin>
        <ymin>0</ymin>
        <xmax>182.22223020067403</xmax>
        <ymax>5.28533050466303</ymax>
    </bndbox>
</object><object>
    <name>nongerminated</name>
    <pose>Unspecified</pose>
    <truncated>0</truncated>
    <difficult>0</difficult>
    <bndbox>
        <xmin>168.366029028799</xmin>
        <ymin>0.3185904872389791</ymin>
        <xmax>174.64053883272058</xmax>
        <ymax>6.330962816136619</ymax>
    </bndbox>
</object><object>
    <name>germinated</name>
    <pose>Unspecified</pose>
    <truncated>0</truncated>
    <difficult>0</difficult>
    <bndbox>
        <xmin>166.27450980392157</xmin>
        <ymin>11.036299243050772</ymin>
        <xmax>174.11764705882354</xmax>
        <ymax>21.2311948346981</ymax>
    </bndbox>
</object><object>
    <name>nongerminated</name>
    <pose>Unspecified</pose>
    <truncated>0</truncated>
    <difficult>0</difficult>
    <bndbox>
        <xmin>168.8888968673407</xmin>
        <ymin>57.30544675751794</ymin>
        <xmax>177.51634784773285</xmax>
        <ymax>64.88625857890896</ymax>
    </bndbox>
</object><object>
    <name>nongerminated</name>
    <pose>Unspecified</pose>
    <truncated>0</truncated>
    <difficult>0</difficult>
    <bndbox>
        <xmin>213.59477922028185</xmin>
        <ymin>100.43769733756434</ymin>
        <xmax>220.13073491115196</xmax>
        <ymax>106.97288283062645</ymax>
    </bndbox>
</object><object>
    <name>germinated</name>
    <pose>Unspecified</pose>
    <truncated>0</truncated>
    <difficult>0</difficult>
    <bndbox>
        <xmin>166.79740157781862</xmin>
        <ymin>121.61171125867804</ymin>
        <xmax>173.59477922028185</xmax>
        <ymax>132.32941403134518</ymax>
    </bndbox>
</object><object>
    <name>germinated</name>
    <pose>Unspecified</pose>
    <truncated>0</truncated>
    <difficult>0</difficult>
    <bndbox>
        <xmin>30.588235294117645</xmin>
        <ymin>59.91951856148492</ymin>
        <xmax>41.56862745098039</xmax>
        <ymax>67.50034234916528</ymax>
    </bndbox>
</object><object>
    <name>nongerminated</name>
    <pose>Unspecified</pose>
    <truncated>0</truncated>
    <difficult>0</difficult>
    <bndbox>
        <xmin>263.52941176470586</xmin>
        <ymin>133.89785950698322</ymin>
        <xmax>271.1111270680147</xmax>
        <ymax>140.95586414735445</ymax>
    </bndbox>
</object><object>
    <name>nongerminated</name>
    <pose>Unspecified</pose>
    <truncated>0</truncated>
    <difficult>0</difficult>
    <bndbox>
        <xmin>218.30066157322304</xmin>
        <ymin>162.91410080628717</ymin>
        <xmax>225.09803921568627</xmax>
        <ymax>169</ymax>
    </bndbox>
</object><object>
    <name>nongerminated</name>
    <pose>Unspecified</pose>
    <truncated>0</truncated>
    <difficult>0</difficult>
    <bndbox>
        <xmin>277.3856368719363</xmin>
        <ymin>135.20491335840072</ymin>
        <xmax>284.96732823988975</xmax>
        <ymax>142.26291799877194</ymax>
    </bndbox>
</object><object>
    <name>nongerminated</name>
    <pose>Unspecified</pose>
    <truncated>0</truncated>
    <difficult>0</difficult>
    <bndbox>
        <xmin>196.60132314644608</xmin>
        <ymin>157.6859571983532</ymin>
        <xmax>203.3987007889093</xmax>
        <ymax>165.52818457654345</ymax>
    </bndbox>
</object><object>
    <name>nongerminated</name>
    <pose>Unspecified</pose>
    <truncated>0</truncated>
    <difficult>0</difficult>
    <bndbox>
        <xmin>138.0392156862745</xmin>
        <ymin>46.84913560907138</ymin>
        <xmax>144.31372549019608</xmax>
        <ymax>53.38433306842282</ymax>
    </bndbox>
</object><object>
    <name>nongerminated</name>
    <pose>Unspecified</pose>
    <truncated>0</truncated>
    <difficult>0</difficult>
    <bndbox>
        <xmin>126.5359556908701</xmin>
        <ymin>8.945040603248259</ymin>
        <xmax>133.0719113817402</xmax>
        <ymax>14.9574129321459</ymax>
    </bndbox>
</object><object>
    <name>nongerminated</name>
    <pose>Unspecified</pose>
    <truncated>0</truncated>
    <difficult>0</difficult>
    <bndbox>
        <xmin>146.40524471507354</xmin>
        <ymin>57.30544675751794</ymin>
        <xmax>152.41830863204657</xmax>
        <ymax>63.84063225058004</ymax>
    </bndbox>
</object><object>
    <name>nongerminated</name>
    <pose>Unspecified</pose>
    <truncated>0</truncated>
    <difficult>0</difficult>
    <bndbox>
        <xmin>79.73856608072917</xmin>
        <ymin>21.754007998862566</ymin>
        <xmax>85.7516419653799</xmax>
        <ymax>27.504982720394977</ymax>
    </bndbox>
</object><object>
    <name>nongerminated</name>
    <pose>Unspecified</pose>
    <truncated>0</truncated>
    <difficult>0</difficult>
    <bndbox>
        <xmin>56.732034122242645</xmin>
        <ymin>55.47558572508066</ymin>
        <xmax>64.05229157092525</xmax>
        <ymax>63.05640951276102</ymax>
    </bndbox>
</object><object>
    <name>nongerminated</name>
    <pose>Unspecified</pose>
    <truncated>0</truncated>
    <difficult>0</difficult>
    <bndbox>
        <xmin>133.59477922028185</xmin>
        <ymin>85.79886890951276</ymin>
        <xmax>139.34642118566174</xmax>
        <ymax>90.24280174591702</ymax>
    </bndbox>
</object><object>
    <name>nongerminated</name>
    <pose>Unspecified</pose>
    <truncated>0</truncated>
    <difficult>0</difficult>
    <bndbox>
        <xmin>134.11764705882354</xmin>
        <ymin>90.24280174591702</ymin>
        <xmax>140.13073491115196</xmax>
        <ymax>95.20954176334106</ymax>
    </bndbox>
</object><object>
    <name>nongerminated</name>
    <pose>Unspecified</pose>
    <truncated>0</truncated>
    <difficult>0</difficult>
    <bndbox>
        <xmin>127.05882352941177</xmin>
        <ymin>102.2675464037123</ymin>
        <xmax>133.59477922028188</xmax>
        <ymax>109.06414745357364</ymax>
    </bndbox>
</object><object>
    <name>nongerminated</name>
    <pose>Unspecified</pose>
    <truncated>0</truncated>
    <difficult>0</difficult>
    <bndbox>
        <xmin>136.9934800091912</xmin>
        <ymin>120.827488520859</ymin>
        <xmax>143.79085765165442</xmax>
        <ymax>127.10127042341121</ymax>
    </bndbox>
</object><object>
    <name>nongerminated</name>
    <pose>Unspecified</pose>
    <truncated>0</truncated>
    <difficult>0</difficult>
    <bndbox>
        <xmin>110.06536745557598</xmin>
        <ymin>133.1136367691642</ymin>
        <xmax>116.86274509803921</xmax>
        <ymax>140.95586414735445</ymax>
    </bndbox>
</object><object>
    <name>nongerminated</name>
    <pose>Unspecified</pose>
    <truncated>0</truncated>
    <difficult>0</difficult>
    <bndbox>
        <xmin>128.366029028799</xmin>
        <ymin>143.83136347440998</ymin>
        <xmax>135.94772039675243</xmax>
        <ymax>152.19639803362003</ymax>
    </bndbox>
</object><object>
    <name>nongerminated</name>
    <pose>Unspecified</pose>
    <truncated>0</truncated>
    <difficult>0</difficult>
    <bndbox>
        <xmin>93.59477922028186</xmin>
        <ymin>103.05176914153132</ymin>
        <xmax>100.3921568627451</xmax>
        <ymax>110.10977378190255</ymax>
    </bndbox>
</object><object>
    <name>nongerminated</name>
    <pose>Unspecified</pose>
    <truncated>0</truncated>
    <difficult>0</difficult>
    <bndbox>
        <xmin>72.15686274509804</xmin>
        <ymin>106.97288283062645</ymin>
        <xmax>79.73856608072917</xmax>
        <ymax>114.03088747099767</ymax>
    </bndbox>
</object><object>
    <name>nongerminated</name>
    <pose>Unspecified</pose>
    <truncated>0</truncated>
    <difficult>0</difficult>
    <bndbox>
        <xmin>51.503271963082106</xmin>
        <ymin>121.87311484918793</ymin>
        <xmax>59.6078431372549</xmax>
        <ymax>128.14690871802947</ymax>
    </bndbox>
</object><object>
    <name>nongerminated</name>
    <pose>Unspecified</pose>
    <truncated>0</truncated>
    <difficult>0</difficult>
    <bndbox>
        <xmin>63.26797784543505</xmin>
        <ymin>146.9682544256861</ymin>
        <xmax>70.58823529411765</xmax>
        <ymax>155.85609616591594</ymax>
    </bndbox>
</object><object>
    <name>nongerminated</name>
    <pose>Unspecified</pose>
    <truncated>0</truncated>
    <difficult>0</difficult>
    <bndbox>
        <xmin>36.33987725949755</xmin>
        <ymin>140.95586414735445</ymin>
        <xmax>42.614387063419116</xmax>
        <ymax>147.22964604990665</ymax>
    </bndbox>
</object><object>
    <name>nongerminated</name>
    <pose>Unspecified</pose>
    <truncated>0</truncated>
    <difficult>0</difficult>
    <bndbox>
        <xmin>29.281053730085784</xmin>
        <ymin>147.22964604990665</ymin>
        <xmax>36.601311178768384</xmax>
        <ymax>154.81048180387634</ymax>
    </bndbox>
</object><object>
    <name>nongerminated</name>
    <pose>Unspecified</pose>
    <truncated>0</truncated>
    <difficult>0</difficult>
    <bndbox>
        <xmin>10.196078431372548</xmin>
        <ymin>140.95586414735445</ymin>
        <xmax>16.209154316023284</xmax>
        <ymax>147.49106160670587</ymax>
    </bndbox>
</object><object>
    <name>nongerminated</name>
    <pose>Unspecified</pose>
    <truncated>0</truncated>
    <difficult>0</difficult>
    <bndbox>
        <xmin>6.0130758846507355</xmin>
        <ymin>144.615586212229</ymin>
        <xmax>11.764705882352942</xmax>
        <ymax>151.15075973900178</ymax>
    </bndbox>
</object>
</annotation>
